curve_dao/__init__.py
curve_dao/addresses.py
curve_dao/ipfs.py
curve_dao/proposals.py
curve_dao/simulate.py
curve_dao/vote_utils.py
curve_dao-1.0.11.dist-info/METADATA
curve_dao-1.0.11.dist-info/WHEEL
curve_dao-1.0.11.dist-info/top_level.txt
curve_dao-1.0.11.dist-info/RECORD
