Metadata-Version: 2.1
Name: curve-dao
Version: 1.0.11
Summary: DAO governance tools for CurveDAO.
Author-email: FiddyResearch <fiddyresearch@gmail.com>
Maintainer-email: FiddyResearch <fiddyresearch@gmail.com>
License: AGPL-3.0-only License
Project-URL: Homepage, https://pypi.org/project/curve-dao/
Project-URL: GitHub, https://github.com/bout3fiddy/curve-dao
Project-URL: Changelog, https://github.com/bout3fiddy/curve-dao/blob/main/CHANGELOG.md
Project-URL: Issues, https://github.com/bout3fiddy/curve-dao/issues
Keywords: ethereum,smart-contracts,evm,vyper,curve-finance,dao,defi
Classifier: Programming Language :: Python :: 3
Classifier: License :: OSI Approved :: MIT License
Classifier: Operating System :: OS Independent
Requires-Python: >=3.10
Requires-Dist: curve-boa==0.1.10.1
Requires-Dist: requests==2.32.3
Requires-Dist: rich==13.8.0
Requires-Dist: strenum==0.4.15
